processor.v
module pipe_MIPS32(clk1, clk2);
    input clk1, clk2; // creating a two phase clock
    reg[31:0] PC, IF_ID_IR, IF_ID_NPC;
    reg[31:0] ID_EX_IR, ID_EX_NPC, ID_EX_A, ID_EX_B, ID_EX_IMM;
    reg[31:0] EX_MEM_IR, EX_MEM_ALUOUT, EX_MEM_B;
    reg[2:0] ID_EX_TYPE,EX_MEM_TYPE, MEM_WB_TYPE;  // these type are the instruction types like Register-register, register-memory like these
    reg EX_MEM_COND;
    reg[31:0] MEM_WB_IR, MEM_WB_ALUOUT, MEM_WB_LMD;

    reg[31:0] REGISTER[0:31];  //register bank of 32 x32
    reg[31:0] MEM[0:1023]; // memory of 1024 x 32

    parameter ADD= 6'b000000, SUB=6'b000001, AND=6'b000010, OR=6'b000011,
    SLT=6'b000100, MUL=6'b000101, HLT=6'b111111, LW=6'b001000, SW=6'b001001, ADDI=6'b001010,
    SUBI=6'b001011, SLTI=6'b001100,
    BNEQZ=6'b001101, BEQZ=6'b001110;

    parameter RR_ALU=3'b000, RM_ALU=3'b001, LOAD=3'b010, STORE=3'b011, 
    BRANCH=3'b100, HALT=3'b101;

    reg HALTED; // set after the HLT instruction iis completed in the WB Stage ie last stage of pipeling
    reg BRANCH_TAKEN; // required to disable instruciton after the branch

    //IF stage
    always @(posedge clk1) begin 
        if(HALTED==0) begin // all this process will occur when halted flag is nt set to q
            if(((EX_MEM_IR[31:26]==BEQZ) && (EX_MEM_COND==1)) || 
             ((EX_MEM_IR[31:26]== BNEQZ) || ( EX_MEM_COND==0))) 
             // this shows when we have tor branch 
            // this condition is that (A==0) where A is the source register 1 ie content of source register is all zero
            // we can branch 1. branch if condition is equal to 1 or brnch if not qual to 0
            // and we also have some condition to fullfill adn double verify the code
             begin 
                IF_ID_IR <= #2 MEM[EX_MEM_ALUOUT];  // here we are not taking next address from PC
                // rather we're taking next instruction from the output of excution stage and from the output of alu
                BRANCH_TAKEN<= #2 1'b1;
                IF_ID_NPC<= #2 EX_MEM_ALUOUT +1; // new oc will be updated to adress we fot from alu output +1
                PC<= #2 EX_MEM_ALUOUT +1;
             end
            else begin 
                IF_ID_IR<= #2 MEM[PC];
                IF_ID_NPC<= #2 PC+1;
                PC<= #2 PC+1;
            end
        end
    end

    // insstruction decode stage
    // in decode we first decode the OPCODE, in this case we have already didi it
    // we prefetch the source and destination registers
    // we're sign extending the 16 bit imm field
    always @(negedge clk2) begin 
        if (HALTED==0) begin 
            if(IF_ID_IR[25:21]==5'b00000) ID_EX_A<=0;  // here we re checking if opcode meant register[0] ehic contains 0,
            // if this conditoin is found be tur, then we directly assign it
            else ID_EX_A <=#2 REGISTER[IF_ID_IR[25:21]]; // loading the value of sources regiser in A
            //"RS1" SRCE REGISTER 1

            if(IF_ID_IR[20:16]== 5'b00000) ID_EX_B<=0; // same happen for B as if A
            else  ID_EX_B<= #2 REGISTER[IF_ID_IR[20:16]]; //"sorce register 2 "B" loaded wih value 
            

            ID_EX_NPC<= #2 IF_ID_NPC;
            ID_EX_IR <= #2 IF_ID_IR;
            ID_EX_IMM <=#2 {{16{IF_ID_IR[15]}}, {IF_ID_IR[15:0]}} ;// SIGN BIT EXTENSION TO MAKE IT 32 BIT LONG
            //here we are replicating sign bit sixteen times which is indicated by the first terem in the bracket==

            case(IF_ID_IR[31:26]) // here we are checking the the meaning of OPCODe, whzt does opcode what to say
            // it meant to explain what does it signify
                ADD, SUB, AND, OR, SLT, MUL: ID_EX_TYPE <= #2 RR_ALU; // register register alu instruction
                ADDI, SUBI, SLTI : ID_EX_TYPE <=#2 RM_ALU; // register memory
                LW: ID_EX_TYPE<= #2 LOAD; // LW MEANS LOAD WORD
                SW: ID_EX_TYPE <=#2 STORE;
                BNEQZ, BEQZ : ID_EX_TYPE <= #2 BRANCH;
                HLT: ID_EX_TYPE <= #2 HALT;
                default: ID_EX_TYPE <= #2 HALT;  // THIS IS THE CASE OF INVALID OPCODE

            endcase
        end
    end

        // now EXECUTION STAGE
        // this is triggered by clock 1

        always @(posedge clk1) begin
            if (HALTED==0) begin 
                EX_MEM_TYPE <= #2 ID_EX_TYPE;
                EX_MEM_IR <= #2 ID_EX_IR;
                BRANCH_TAKEN<= #2 0;

                case(ID_EX_TYPE)
                    RR_ALU: begin 
                        case(ID_EX_IR[31:26]) //OPCODE
                            ADD: EX_MEM_ALUOUT<= ID_EX_A + ID_EX_B;
                            SUB: EX_MEM_ALUOUT<= ID_EX_A - ID_EX_B;
                            AND: EX_MEM_ALUOUT<= ID_EX_A & ID_EX_B;
                            OR: EX_MEM_ALUOUT<= ID_EX_A | ID_EX_B;
                            SLT: EX_MEM_ALUOUT<= ID_EX_A < ID_EX_B;
                            MUL: EX_MEM_ALUOUT<= ID_EX_A * ID_EX_B;
                            default: EX_MEM_ALUOUT<= 32'hxxxxxxxx;


                        endcase
                    end
                    RM_ALU: begin 
                        case(ID_EX_IR[31:26]) //opcode
                            ADDI: EX_MEM_ALUOUT<= ID_EX_A + ID_EX_IMM;
                            SUBI: EX_MEM_ALUOUT<= ID_EX_A - ID_EX_IMM;
                            SLTI: EX_MEM_ALUOUT<= ID_EX_A < ID_EX_IMM;
                            default: EX_MEM_ALUOUT<= 32'hxxxxxxxx;
                            

                        endcase
                    end

                    LOAD, STORE:
                        begin 
                            EX_MEM_ALUOUT <= #2 ID_EX_A + ID_EX_IMM;
                            EX_MEM_B <= #2 ID_EX_B;
                        end
                    
                    BRANCH: begin
                        EX_MEM_ALUOUT <= #2 ID_EX_NPC + ID_EX_IMM;
                        EX_MEM_COND <= #2 (ID_EX_A ==0);
                    end
                    
                endcase
            end 
        end

        //mem stage

        always @(posedge clk2) begin
            if (HALTED==0 )begin 
                MEM_WB_TYPE <=#2 EX_MEM_TYPE; // these paramets are forwarded to next stage
                MEM_WB_IR <= #2 EX_MEM_IR;// this also

                case(EX_MEM_TYPE) 
                    RR_ALU, RM_ALU:
                        MEM_WB_ALUOUT <= #2 EX_MEM_ALUOUT;
                    LOAD: MEM_WB_LMD <= #2 MEM[EX_MEM_ALUOUT];
                    STORE: if(BRANCH_TAKEN==0) begin // DISABEL WRITE when it is o
                            MEM[EX_MEM_ALUOUT] <= #2 EX_MEM_B;
                    end
                endcase
            end
        end

        //WB stage(write back stage)
        always @(posedge clk1) begin 
            if(BRANCH_TAKEN==0 ) begin 
                case(MEM_WB_TYPE==0) // DISABLE WRITE IF BRANCH IS TAKEN
                    RR_ALU: REGISTER[MEM_WB_IR[15:11]] <=#2 MEM_WB_ALUOUT; // "rd"
                    RM_ALU: REGISTER[MEM_WB_IR[20:16]] <= #2 MEM_WB_ALUOUT; //" rt"\
                    LOAD: REGISTER[MEM_WB_IR[20:16]] <= #2 MEM_WB_LMD; // "RT"
                    HALT: HALTED <= #2 1'b1;
                endcase
            end
        end
        
endmodule

processor_tb.v
`include "processor.v"

module test();
    reg clk1, clk2,PC;
    integer k;
    pipe_MIPS32 mips(clk1, clk2);

    initial begin 
        clk1=0; 
        clk2=0;
        repeat(20) begin 
            #5 clk1=1; #5 clk1=0;  // generating two phase clocks
            #5 clk2=1; #5 clk2=0;
        end
    end

    initial begin 
        for(k=0; k<31; k=k+1) begin 
            mips.REGISTER[k]=k; // innitiasiling the GPR 
            // here we are reffereing to pipl_MIPS32 's registers which are 
            // general purpose register.. 
            // we do refernce using as here we want to refer REGISTER of mips ie pipe_MIPS
            // so we used the mps. REGISTER[k]
        end
        mips.MEM[0]= 32'h2801000a;  //ADDI R1, R0,10   here we are feeding instructions in memory
        mips.MEM[1]= 32'h28020012 ; //ADDI R2, R0, 20
        mips.MEM[2]= 32'h28030019  ; // ADDI R3, R0, 25
        // dummy instruction inserted to deal with data hazard
        mips.MEM[3]= 32'h0ce77800;/// **DUMMY INSTRUCTOIN** OR R7, R7, R7  
        mips.MEM[4]= 32'h0ce7800; // dummy instru
        mips.MEM[5]= 32'h00222000;  // ADD R4, R1, R2
        mips.MEM[6]= 32'h0ce77800;  // or instruction DUMMY]
        mips.MEM[7]= 32'h00832800;   // ADD R5, R4, R3
        mips.MEM[8]= 32'hfc000000;    // HLT

        // setting halted , oc and branck taken to 0
        mips.HALTED=0;
        mips.PC=0;
        mips. BRANCH_TAKEN=0;

        #280
        for(k=0; k<8; k=k+1) begin 
             $display("R%1d - %2d", k, mips. REGISTER[k]);
        end

        end

        initial begin 
            $dumpfile("mips.vcd");
            $dumpvars(0,test);
            $dumpvars(0,test.PC);
            #300 $finish;
        end


endmodule

mips.vcd
$date
	Mon Jul 22 03:13:47 2024
$end
$version
	Icarus Verilog
$end
$timescale
	1s
$end
$scope module test $end
$var reg 1 ! PC $end
$var reg 1 " clk1 $end
$var reg 1 # clk2 $end
$var integer 32 $ k [31:0] $end
$scope module mips $end
$var wire 1 " clk1 $end
$var wire 1 # clk2 $end
$var reg 1 % BRANCH_TAKEN $end
$var reg 32 & EX_MEM_ALUOUT [31:0] $end
$var reg 32 ' EX_MEM_B [31:0] $end
$var reg 1 ( EX_MEM_COND $end
$var reg 32 ) EX_MEM_IR [31:0] $end
$var reg 3 * EX_MEM_TYPE [2:0] $end
$var reg 1 + HALTED $end
$var reg 32 , ID_EX_A [31:0] $end
$var reg 32 - ID_EX_B [31:0] $end
$var reg 32 . ID_EX_IMM [31:0] $end
$var reg 32 / ID_EX_IR [31:0] $end
$var reg 32 0 ID_EX_NPC [31:0] $end
$var reg 3 1 ID_EX_TYPE [2:0] $end
$var reg 32 2 IF_ID_IR [31:0] $end
$var reg 32 3 IF_ID_NPC [31:0] $end
$var reg 32 4 MEM_WB_ALUOUT [31:0] $end
$var reg 32 5 MEM_WB_IR [31:0] $end
$var reg 32 6 MEM_WB_LMD [31:0] $end
$var reg 3 7 MEM_WB_TYPE [2:0] $end
$var reg 32 8 PC [31:0] $end
$upscope $end
$upscope $end
$enddefinitions $end
#0
$dumpvars
b0 8
bx 7
bx 6
bx 5
bx 4
bx 3
bx 2
bx 1
bx 0
bx /
bx .
bx -
bx ,
0+
bx *
bx )
x(
bx '
bx &
0%
b11111 $
0#
0"
x!
$end
#2
b101 1
#5
1"
#7
b1 8
b1 3
b101000000000010000000000001010 2
b101 *
#10
0"
#15
1#
#17
b101 7
#20
b0 ,
0#
#22
b1 1
b1010 .
b101000000000010000000000001010 /
b1 0
b1 -
#25
b1010 &
1"
#27
b101000000000010000000000001010 )
b1 *
b10 8
b10 3
b101000000000100000000000010010 2
#30
0"
#35
1#
#37
b1010 4
b101000000000010000000000001010 5
b1 7
#40
0#
#42
b10010 .
b101000000000100000000000010010 /
b10 0
b10 -
#45
b10010 &
1"
#47
b11 8
b11 3
b101000000000110000000000011001 2
b101000000000100000000000010010 )
#50
0"
#55
1#
#57
b10010 4
b101000000000100000000000010010 5
#60
0#
#62
b11001 .
b101000000000110000000000011001 /
b11 0
b11 -
#65
b11001 &
1"
#67
b101000000000110000000000011001 )
b100 8
b100 3
b1100111001110111100000000000 2
#70
0"
#75
1#
#77
b11001 4
b101000000000110000000000011001 5
#80
0#
#82
b0 1
b111100000000000 .
b1100111001110111100000000000 /
b100 0
b111 -
b111 ,
#85
b111 &
1"
#87
b101 8
b101 3
b110011100111100000000000 2
b1100111001110111100000000000 )
b0 *
#90
0"
#95
1#
#97
b111 4
b1100111001110111100000000000 5
b0 7
#100
0#
#102
b110011100111100000000000 /
b101 0
b1110 -
b110 ,
#105
b10100 &
1"
#107
b110011100111100000000000 )
b110 8
b110 3
b1000100010000000000000 2
#110
0"
#115
1#
#117
b10100 4
b110011100111100000000000 5
#120
0#
#122
b10000000000000 .
b1000100010000000000000 /
b110 0
b10 -
b1 ,
#125
b11 &
1"
#127
b111 8
b111 3
b1100111001110111100000000000 2
b1000100010000000000000 )
#130
0"
#135
1#
#137
b11 4
b1000100010000000000000 5
#140
0#
#142
b111100000000000 .
b1100111001110111100000000000 /
b111 0
b111 -
b111 ,
#145
b111 &
1"
#147
b1100111001110111100000000000 )
b1000 8
b1000 3
b100000110010100000000000 2
#150
0"
#155
1#
#157
b111 4
b1100111001110111100000000000 5
#160
0#
#162
b10100000000000 .
b100000110010100000000000 /
b1000 0
b11 -
b100 ,
#165
1"
#167
b1001 8
b1001 3
b11111100000000000000000000000000 2
b100000110010100000000000 )
#170
0"
#175
1#
#177
b100000110010100000000000 5
#180
b0 -
b0 ,
0#
#182
b101 1
b0 .
b11111100000000000000000000000000 /
b1001 0
#185
1"
#187
b11111100000000000000000000000000 )
b101 *
b1010 8
b1010 3
bx 2
#190
0"
#195
1#
#197
b11111100000000000000000000000000 5
b101 7
#200
0#
#202
bx .
bx /
b1010 0
bx -
bx ,
#205
1"
#207
b1011 8
b1011 3
bx )
#210
0"
#215
1#
#217
bx 5
#220
0#
#222
b1011 0
#225
1"
#227
b1100 8
b1100 3
#230
0"
#235
1#
#240
0#
#242
b1100 0
#245
1"
#247
b1101 8
b1101 3
#250
0"
#255
1#
#260
0#
#262
b1101 0
#265
1"
#267
b1110 8
b1110 3
#270
0"
#275
1#
#280
0#
b1000 $
#282
b1110 0
#285
1"
#287
b1111 8
b1111 3
